age/VERSION.py
age/__init__.py
age/age.py
age/builder.py
age/exceptions.py
age/models.py
age/gen/AgtypeLexer.py
age/gen/AgtypeListener.py
age/gen/AgtypeParser.py
age/gen/AgtypeVisitor.py
age/gen/__init__.py
apache_age_python-0.0.7.dist-info/LICENSE
apache_age_python-0.0.7.dist-info/METADATA
apache_age_python-0.0.7.dist-info/WHEEL
apache_age_python-0.0.7.dist-info/top_level.txt
apache_age_python-0.0.7.dist-info/RECORD
