Metadata-Version: 2.1
Name: apache-age-python
Version: 0.0.7
Summary: Python driver support for Apache AGE
Home-page: https://github.com/apache/age/tree/master/drivers/python
Download-URL: https://github.com/apache/age/releases
Author: Ikchan Kwon, Apache AGE
Author-email: dev-subscribe@age.apache.org
License: Apache2.0
Keywords: Graph Database,Apache AGE,PostgreSQL
Classifier: Programming Language :: Python :: 3.9
Requires-Python: >=3.9
License-File: LICENSE
Requires-Dist: psycopg2
Requires-Dist: antlr4-python3-runtime ==4.11.1
